flask_sessionstore/__init__.py
flask_sessionstore/sessions.py
Flask_Sessionstore3-0.4.8.dist-info/LICENSE
Flask_Sessionstore3-0.4.8.dist-info/METADATA
Flask_Sessionstore3-0.4.8.dist-info/WHEEL
Flask_Sessionstore3-0.4.8.dist-info/top_level.txt
Flask_Sessionstore3-0.4.8.dist-info/RECORD
