Metadata-Version: 2.1
Name: Flask-Sessionstore3
Version: 0.4.8
Summary: Adds session support to your Flask application, upgraded to Flask 2.0
Home-page: https://github.com/fgiamma/flask-sessionstore3
Author: Fabrizio Giammatteo
Author-email: fabrizio.giammatteo@gmail.com
License: BSD
Platform: any
Classifier: Environment :: Web Environment
Classifier: Intended Audience :: Developers
Classifier: License :: OSI Approved :: BSD License
Classifier: Operating System :: OS Independent
Classifier: Programming Language :: Python :: 2
Classifier: Programming Language :: Python :: 3
Classifier: Topic :: Internet :: WWW/HTTP :: Dynamic Content
Classifier: Topic :: Software Development :: Libraries :: Python Modules
License-File: LICENSE
Requires-Dist: Flask (>=0.8)
Requires-Dist: cachelib (>=0.1.1)
